Metadata-Version: 2.1
Name: pyplotsixel
Version: 0.2.0
Summary: Matplotlib sixel backend
Home-page: https://github.com/nakagami/pyplotsixel
Author: Hajime Nakagami
Author-email: nakagami@gmail.com
License: BSD
Keywords: matplotlib,sixel
License-File: LICENSE
